pybytes/__init__.py
pybytes/core.py
pybytes-0.1.0.dist-info/licenses/LICENCE
pybytes-0.1.0.dist-info/METADATA
pybytes-0.1.0.dist-info/WHEEL
pybytes-0.1.0.dist-info/top_level.txt
pybytes-0.1.0.dist-info/RECORD
